{
    "$schema": "https://schema.management.azure.com/schemas/2015-01-01/deploymentParameters.json#",
    "contentVersion": "1.0.0.0",
    "parameters": {
        "location": {
            "value": "westeurope"
        },
        "networkInterfaceName": {
            "value": "testvm1493"
        },
        "networkSecurityGroupName": {
            "value": "TestVM1-nsg"
        },
        "networkSecurityGroupRules": {
            "value": [
                {
                    "name": "RDP",
                    "properties": {
                        "priority": 300,
                        "protocol": "TCP",
                        "access": "Allow",
                        "direction": "Inbound",
                        "sourceAddressPrefix": "*",
                        "sourcePortRange": "*",
                        "destinationAddressPrefix": "*",
                        "destinationPortRange": "3389"
                    }
                }
            ]
        },
        "subnetName": {
            "value": "default"
        },
        "virtualNetworkId": {
            "value": "/subscriptions/db63ea1e-b8d2-4898-a6a3-647c94c9d70b/resourceGroups/GWS-DevTestLabs/providers/Microsoft.Network/virtualNetworks/DtlPOC-Lab1"
        },
        "publicIpAddressName": {
            "value": "TestVM1-ip"
        },
        "publicIpAddressType": {
            "value": "Dynamic"
        },
        "publicIpAddressSku": {
            "value": "Basic"
        },
        "virtualMachineName": {
            "value": "TestVM1"
        },
        "virtualMachineComputerName": {
            "value": "TestVM1"
        },
        "virtualMachineRG": {
            "value": "GWS-DevTestLabs"
        },
        "osDiskType": {
            "value": "StandardSSD_LRS"
        },
        "virtualMachineSize": {
            "value": "Standard_D2s_v3"
        },
        "adminUsername": {
            "value": "devuser1"
        },
        "adminPassword": {
		"reference": {
		"keyVault": {
		"id": "poclabfde06612"
		},
		"secretName": "VmPassword"
		},
        "patchMode": {
            "value": "AutomaticByOS"
        },
        "enableHotpatching": {
            "value": false
        },
        "autoShutdownStatus": {
            "value": "Enabled"
        },
        "autoShutdownTime": {
            "value": "19:00"
        },
        "autoShutdownTimeZone": {
            "value": "UTC"
        },
        "autoShutdownNotificationStatus": {
            "value": "Disabled"
        },
        "autoShutdownNotificationLocale": {
            "value": "en"
        }
    }
}